Metadata-Version: 2.4
Name: x_4357_make_telemetry_vector_x
Version: 0.20.17
Summary: Shared telemetry normalization utilities for the visitor constellation.
Author-email: "RRGM (Software Tech Lead, Primus Pilus Night Watch AI Corp.)" <foo@bar.com>
Requires-Python: >=3.8
Requires-Dist: pydantic>=2.6
Requires-Dist: typing-extensions>=4.9
